<?xml version="1.0"?>
<testResults>
  <FitNesseVersion>v20140915</FitNesseVersion>
  <rootPath>IdmFitNesse.BasicSetup.ConnectionSetup</rootPath>
    <result>
    <counts>
      <right>0</right>
      <wrong>0</wrong>
      <ignores>0</ignores>
      <exceptions>1</exceptions>
    </counts>
    <runTimeInMillis>4</runTimeInMillis>
    <content>&lt;br/&gt;&amp;lt;test page&amp;gt;&lt;br/&gt;&lt;table&gt;
	&lt;tr&gt;
		&lt;td colspan="4" class="error"&gt;de.guh.IdmFitnesse.ldap.LdapSetupFixture&lt;hr&gt;&lt;pre&gt;&lt;div class="fit_stacktrace"&gt;java.lang.NoClassDefFoundError: fitlibrary/SetUpFixture
	at java.lang.ClassLoader.defineClass1(Native Method)
	at java.lang.ClassLoader.defineClass(Unknown Source)
	at java.security.SecureClassLoader.defineClass(Unknown Source)
	at java.net.URLClassLoader.defineClass(Unknown Source)
	at java.net.URLClassLoader.access$100(Unknown Source)
	at java.net.URLClassLoader$1.run(Unknown Source)
	at java.net.URLClassLoader$1.run(Unknown Source)
	at java.security.AccessController.doPrivileged(Native Method)
	at java.net.URLClassLoader.findClass(Unknown Source)
	at java.lang.ClassLoader.loadClass(Unknown Source)
	at sun.misc.Launcher$AppClassLoader.loadClass(Unknown Source)
	at java.lang.ClassLoader.loadClass(Unknown Source)
	at java.lang.Class.forName0(Native Method)
	at java.lang.Class.forName(Unknown Source)
	at fit.FixtureLoader.loadFixtureClass(FixtureLoader.java:67)
	at fit.FixtureLoader.instantiateFixture(FixtureLoader.java:60)
	at fit.FixtureLoader.instantiateFirstValidFixtureClass(FixtureLoader.java:84)
	at fit.FixtureLoader.disgraceThenLoad(FixtureLoader.java:44)
	at fit.Fixture.loadFixture(Fixture.java:141)
	at fit.Fixture.getLinkedFixtureWithArgs(Fixture.java:133)
	at fit.Fixture.doTables(Fixture.java:78)
	at fit.FitServer.process(FitServer.java:81)
	at fit.FitServer.run(FitServer.java:56)
	at fit.FitServer.main(FitServer.java:41)
Caused by: java.lang.ClassNotFoundException: fitlibrary.SetUpFixture
	at java.net.URLClassLoader$1.run(Unknown Source)
	at java.net.URLClassLoader$1.run(Unknown Source)
	at java.security.AccessController.doPrivileged(Native Method)
	at java.net.URLClassLoader.findClass(Unknown Source)
	at java.lang.ClassLoader.loadClass(Unknown Source)
	at sun.misc.Launcher$AppClassLoader.loadClass(Unknown Source)
	at java.lang.ClassLoader.loadClass(Unknown Source)
	... 24 more
&lt;/div&gt;&lt;/pre&gt;&lt;/td&gt;
	&lt;/tr&gt;
	&lt;tr&gt;
		&lt;td&gt;name&lt;/td&gt;
		&lt;td&gt;BindDN&lt;/td&gt;
		&lt;td&gt;BindPW&lt;/td&gt;
		&lt;td&gt;LdapURL&lt;/td&gt;
	&lt;/tr&gt;
	&lt;tr&gt;
		&lt;td&gt;localDS&lt;/td&gt;
		&lt;td&gt;admin&lt;/td&gt;
		&lt;td&gt;secret&lt;/td&gt;
		&lt;td&gt;ldap://localhost:10389/&lt;/td&gt;
	&lt;/tr&gt;
&lt;/table&gt;
&lt;br/&gt;</content>
    <relativePageName>ConnectionSetup</relativePageName>
          </result>
      <finalCounts>
    <right>0</right>
    <wrong>0</wrong>
    <ignores>0</ignores>
    <exceptions>1</exceptions>
  </finalCounts>
  <totalRunTimeInMillis>4</totalRunTimeInMillis>
  
</testResults>

